nanome_workspace_manager/WorkspaceManager.py
nanome_workspace_manager/__init__.py
nanome_workspace_manager/menu.json
nanome_workspace_manager-0.1.1.dist-info/LICENSE
nanome_workspace_manager-0.1.1.dist-info/METADATA
nanome_workspace_manager-0.1.1.dist-info/WHEEL
nanome_workspace_manager-0.1.1.dist-info/entry_points.txt
nanome_workspace_manager-0.1.1.dist-info/top_level.txt
nanome_workspace_manager-0.1.1.dist-info/RECORD
