Metadata-Version: 2.1
Name: nanome-workspace-manager
Version: 0.1.1
Summary: Nanome Plugin allowing standalone VR headset users to save and load workspaces in a central location
Home-page: https://github.com/nanome-ai/plugin-workspace-manager
Author: Nanome
Author-email: hello@nanome.ai
License: MIT
Keywords: virtual-reality,chemistry,python,api,plugin
Platform: any
Classifier: Development Status :: 3 - Alpha
Classifier: Intended Audience :: Science/Research
Classifier: Topic :: Scientific/Engineering :: Chemistry
Classifier: License :: OSI Approved :: MIT License
Classifier: Programming Language :: Python :: 2.7
Classifier: Programming Language :: Python :: 3.5
Classifier: Programming Language :: Python :: 3.6
Classifier: Programming Language :: Python :: 3.7
Requires-Dist: nanome
